sage/examples/README.md
sage/examples/STRUCTURE.md
sage/examples/__init__.py
sage/examples/agents/__init__.py
sage/examples/agents/multiagent_app.py
sage/examples/evaluation/README.md
sage/examples/evaluation/__init__.py
sage/examples/evaluation/qa_evaluate.py
sage/examples/memory/README.md
sage/examples/memory/__init__.py
sage/examples/memory/biology_rag_knowledge.py
sage/examples/memory/external_memory_ingestion_pipeline.py
sage/examples/memory/mem_examples.py
sage/examples/memory/mem_offline_write.py
sage/examples/memory/mem_offline_write_test.py
sage/examples/memory/memqa.py
sage/examples/memory/raw_qa_insert.py
sage/examples/memory/experiment/config/config_locomo_memprompt.yaml
sage/examples/memory/experiment/function/locomo.py
sage/examples/memory/experiment/memrun/locomo_memprompt_run.py
sage/examples/memory/experiment/prefill/locomo_memprompt_prefill.py
sage/examples/rag/README.md
sage/examples/rag/__init__.py
sage/examples/rag/qa_batch.py
sage/examples/rag/qa_bm25_retrieval.py
sage/examples/rag/qa_bm25_retrieval_edit.py
sage/examples/rag/qa_dense_retrieval copy.py
sage/examples/rag/qa_dense_retrieval.py
sage/examples/rag/qa_dense_retrieval_mixed.py
sage/examples/rag/qa_dense_retrieval_ray.py
sage/examples/rag/qa_hf.py
sage/examples/rag/qa_multiplex.py
sage/examples/rag/qa_openai.py
sage/examples/rag/qa_openai_chat_history.py
sage/examples/rag/qa_refiner.py
sage/examples/rag/qa_rerank.py
sage/examples/rag/qa_source.py
sage/examples/rag/rag.py
sage/examples/rag/rag_simple.py
sage/examples/resources/README.md
sage/examples/resources/__init__.py
sage/examples/resources/config/README.md
sage/examples/resources/config/config.yaml
sage/examples/resources/config/config_adaptive.yaml
sage/examples/resources/config/config_batch.yaml
sage/examples/resources/config/config_bm25s.yaml
sage/examples/resources/config/config_enhanced.yaml
sage/examples/resources/config/config_evaluate.yaml
sage/examples/resources/config/config_for_ingest.yaml
intsage_userspace-1.0.0.dist-info/METADATA
intsage_userspace-1.0.0.dist-info/WHEEL
intsage_userspace-1.0.0.dist-info/top_level.txt
intsage_userspace-1.0.0.dist-info/RECORD
