Metadata-Version: 2.4
Name: intsage-userspace
Version: 1.0.0
Summary: SAGE Framework - 用户空间组件 (合并 sage-lib, sage-plugins 和 sage-examples)
Author-email: IntelliStream Team <intellistream@outlook.com>
License: MIT
Project-URL: Homepage, https://github.com/intellistream/SAGE
Project-URL: Repository, https://github.com/intellistream/SAGE.git
Project-URL: Documentation, https://intellistream.github.io/SAGE-Pub/
Project-URL: Issues, https://github.com/intellistream/SAGE/issues
Keywords: library,framework,plugins,rag,intellistream,ai,algorithms,llm,extensions,data,ecosystem,sage,ml,components
Classifier: Development Status :: 4 - Beta
Classifier: Intended Audience :: Developers
Classifier: Intended Audience :: Science/Research
Classifier: License :: OSI Approved :: MIT License
Classifier: Operating System :: OS Independent
Classifier: Programming Language :: Python :: 3
Classifier: Programming Language :: Python :: 3.10
Classifier: Programming Language :: Python :: 3.11
Classifier: Programming Language :: Python :: 3.12
Classifier: Topic :: Scientific/Engineering :: Artificial Intelligence
Classifier: Topic :: Software Development :: Libraries :: Python Modules
Classifier: Topic :: System :: Distributed Computing
Requires-Python: >=3.10
Requires-Dist: intellistream-sage-kernel
Requires-Dist: intellistream-sage-middleware
Requires-Dist: tiktoken
Requires-Dist: sentence_transformers>=3.1.1
Requires-Dist: einops
Requires-Dist: outlines
Requires-Dist: sentencepiece
Requires-Dist: rouge==1.0.1
Requires-Dist: fitz==0.0.1.dev2
Requires-Dist: scikit-learn>=1.3.0
Requires-Dist: sympy>=1.12
Requires-Dist: networkx==3.4.2
Requires-Dist: joblib>=1.3.0
Requires-Dist: polars>=0.20.0
Requires-Dist: pyarrow>=12.0.0
Requires-Dist: aiofiles>=0.8.0
Requires-Dist: importlib-metadata>=4.0.0
Requires-Dist: stevedore>=5.0.0
Requires-Dist: pluggy>=1.0.0
Requires-Dist: entrypoints>=0.4
Provides-Extra: vectordb
Requires-Dist: chromadb>=0.4.0; extra == "vectordb"
Requires-Dist: qdrant-client>=1.0.0; extra == "vectordb"
Requires-Dist: weaviate-client>=3.0.0; extra == "vectordb"
Requires-Dist: pinecone-client>=2.0.0; extra == "vectordb"
Provides-Extra: advanced
Requires-Dist: optuna>=3.0.0; extra == "advanced"
Requires-Dist: hyperopt>=0.2.7; extra == "advanced"
Requires-Dist: bayesian-optimization>=1.4.0; extra == "advanced"
Requires-Dist: scikit-optimize>=0.9.0; extra == "advanced"
Provides-Extra: graph
Requires-Dist: igraph>=0.10.0; extra == "graph"
Requires-Dist: graph-tool>=2.45; extra == "graph"
Requires-Dist: networkit>=10.1; extra == "graph"
Provides-Extra: math
Requires-Dist: cvxpy>=1.3.0; extra == "math"
Requires-Dist: gekko>=1.0.6; extra == "math"
Requires-Dist: pulp>=2.7.0; extra == "math"
Provides-Extra: graphdb
Requires-Dist: neo4j>=5.0.0; extra == "graphdb"
Requires-Dist: networkx==3.4.2.0; extra == "graphdb"
Provides-Extra: rag
Requires-Dist: langchain>=0.1.0; extra == "rag"
Requires-Dist: llama-index>=0.9.0; extra == "rag"
Provides-Extra: llm
Requires-Dist: openai>=1.0.0; extra == "llm"
Requires-Dist: anthropic>=0.3.0; extra == "llm"
Requires-Dist: google-generativeai>=0.3.0; extra == "llm"
Requires-Dist: cohere>=4.0.0; extra == "llm"
Provides-Extra: embedding
Requires-Dist: sentence-transformers>=2.2.0; extra == "embedding"
Requires-Dist: openai>=1.0.0; extra == "embedding"
Requires-Dist: cohere>=4.0.0; extra == "embedding"
Provides-Extra: storage
Requires-Dist: redis>=4.5.0; extra == "storage"
Requires-Dist: pymongo>=4.0.0; extra == "storage"
Requires-Dist: elasticsearch>=8.0.0; extra == "storage"
Provides-Extra: network
Requires-Dist: httpx>=0.24.0; extra == "network"
Requires-Dist: websockets>=11.0.0; extra == "network"
Requires-Dist: kafka-python>=2.0.0; extra == "network"
Provides-Extra: testing
Requires-Dist: pytest>=7.0.0; extra == "testing"
Requires-Dist: pytest-asyncio>=0.21.0; extra == "testing"
Requires-Dist: pytest-cov>=4.0.0; extra == "testing"
Requires-Dist: pytest-benchmark>=4.0.0; extra == "testing"
Requires-Dist: pytest-mock>=3.10.0; extra == "testing"
Provides-Extra: full
Requires-Dist: sage-userspace[advanced,embedding,graph,graphdb,llm,math,network,rag,storage,testing,vectordb]; extra == "full"
